pictionnary_httpd/__init__.py
pictionnary_httpd/config.py
pictionnary_httpd/forms.py
pictionnary_httpd/game.py
pictionnary_httpd/routes.py
pictionnary_httpd/static/arrow_down.png
pictionnary_httpd/static/arrow_idle.png
pictionnary_httpd/static/discussion.js
pictionnary_httpd/static/graphics.js
pictionnary_httpd/static/jquery-3.5.1.js
pictionnary_httpd/static/jquery-3.5.1.min.js
pictionnary_httpd/static/pictionnary.js
pictionnary_httpd/static/pixi.js
pictionnary_httpd/static/player.js
pictionnary_httpd/static/pret_down.jpg
pictionnary_httpd/static/pret_up.jpg
pictionnary_httpd/static/socket.io.js
pictionnary_httpd/static/style.css
pictionnary_httpd/static/widgets.js
pictionnary_httpd/templates/_formhelpers.html
pictionnary_httpd/templates/choseUsername.html
pictionnary_httpd/templates/game.html
pictionnary_httpd/templates/home.html
pictionnary_httpd/var/liste.txt
pyctionnary-0.2.0a1.data/scripts/pictionnaryd.sh
pyctionnary-0.2.0a1.data/scripts/pyctionnary.py
pyctionnary-0.2.0a1.dist-info/METADATA
pyctionnary-0.2.0a1.dist-info/WHEEL
pyctionnary-0.2.0a1.dist-info/top_level.txt
pyctionnary-0.2.0a1.dist-info/RECORD
